lol_stats/__init__.py
lol_stats/launch.py
lol_stats/launcher.py
lol_stats/program.py
lol_stats/data/faker.pkl
lol_stats/templates/index.html
lol_stats-1.0.1.dist-info/METADATA
lol_stats-1.0.1.dist-info/WHEEL
lol_stats-1.0.1.dist-info/top_level.txt
lol_stats-1.0.1.dist-info/RECORD
