Metadata-Version: 2.1
Name: lol-stats
Version: 1.0.1
Summary: Extract text from a YouTube video in a single command, using OpenAi's Whisper speech recognition model
Home-page: https://github.com/atahanuz/lol-stats
Author: Atahan Uz
Author-email: atahanuz23@gmail.com
Classifier: Programming Language :: Python :: 3
Classifier: License :: OSI Approved :: MIT License
Classifier: Operating System :: OS Independent
Requires-Dist: Flask
Requires-Dist: numpy
Requires-Dist: selenium
Requires-Dist: beautifulsoup4
Requires-Dist: pandas
Requires-Dist: webdriver-manager
